{"trial_id": "1", "hyperparameters": {"space": [{"class_name": "Choice", "config": {"name": "optimizer", "default": "adam", "conditions": [], "values": ["adam", "sgd", "rmsprop", "adadelta"], "ordered": false}}], "values": {"optimizer": "rmsprop"}}, "metrics": {"metrics": {"accuracy": {"direction": "max", "observations": [{"value": [0.7622149586677551], "step": 9}]}, "loss": {"direction": "min", "observations": [{"value": [0.4785562753677368], "step": 9}]}, "val_accuracy": {"direction": "max", "observations": [{"value": [0.7467532753944397], "step": 9}]}, "val_loss": {"direction": "min", "observations": [{"value": [0.5272050499916077], "step": 9}]}}}, "score": 0.7467532753944397, "best_step": 9, "status": "COMPLETED", "message": null}